constants/__init__.py
constants/functions.py
constants/values.py
importantconstantsforstudy_yuvneil-0.0.1.dist-info/METADATA
importantconstantsforstudy_yuvneil-0.0.1.dist-info/WHEEL
importantconstantsforstudy_yuvneil-0.0.1.dist-info/top_level.txt
importantconstantsforstudy_yuvneil-0.0.1.dist-info/RECORD
